pyproject_indirect_import_detector/__init__.py
pyproject_indirect_import_detector/__main__.py
pyproject_indirect_import_detector/detector.py
pyproject_indirect_import_detector/domain.py
pyproject_indirect_import_detector/exception.py
pyproject_indirect_import_detector/main.py
pyproject_indirect_import_detector/py.typed
pyproject_indirect_import_detector/pyproject.py
pyproject_indirect_import_detector/result.py
pyproject_indirect_import_detector/util.py
pyproject_indirect_import_detector-0.1.2.dist-info/entry_points.txt
pyproject_indirect_import_detector-0.1.2.dist-info/LICENSE.txt
pyproject_indirect_import_detector-0.1.2.dist-info/WHEEL
pyproject_indirect_import_detector-0.1.2.dist-info/METADATA
pyproject_indirect_import_detector-0.1.2.dist-info/RECORD
