Metadata-Version: 2.1
Name: pyproject-indirect-import-detector
Version: 0.1.2
Summary: CI tool to detect indirect import
Home-page: https://github.com/kenoss/pyproject-indirect-import-detector
License: MIT
Keywords: python3,linter,styleguide
Author: keno
Author-email: keno.ss57@gmail.com
Requires-Python: >=3.6,<4.0
Classifier: Development Status :: 3 - Alpha
Classifier: Intended Audience :: Developers
Classifier: License :: OSI Approved :: MIT License
Classifier: Programming Language :: Python :: 3
Classifier: Programming Language :: Python :: 3 :: Only
Classifier: Programming Language :: Python :: 3.6
Classifier: Programming Language :: Python :: 3.7
Classifier: Programming Language :: Python :: 3.8
Classifier: Programming Language :: Python :: 3.9
Classifier: Topic :: Software Development :: Libraries
Classifier: Topic :: Software Development :: Quality Assurance
Requires-Dist: result (>=0.6.0,<0.7.0)
Requires-Dist: setuptools (>=56.0.0,<57.0.0)
Requires-Dist: stdlib-list (>=0.8.0,<0.9.0)
Requires-Dist: termcolor (>=1.1.0,<2.0.0)
Requires-Dist: toml (>=0.10.2,<0.11.0)
Project-URL: Repository, https://github.com/kenoss/pyproject-indirect-import-detector
